hw2_spy/__init__.py
hw2_spy/__main__.py
hw2_spy/hw2_spy_config.py
hw2_spy/hw2_spy_data.py
hw2_spy/hw2_spy_tui.py
hw2_spy/hw2_spy_tui.tcss
hw2_spy/samples/csr_designations.json
hw2_spy/samples/game-objects.json
hw2_spy/samples/get_samples.sh
hw2_spy/samples/leaders.json
hw2_spy/samples/match_events.json
hw2_spy/samples/match_result.json
hw2_spy/samples/player_match_history.json
hw2_spy/samples/player_playlist_ratings.json
hw2_spy/samples/player_season_stats_summary.json
hw2_spy/samples/player_stats_summary.json
hw2_spy/samples/player_xps.json
hw2_spy/samples/playlists.json
hw2_spy/samples/spartan-ranks.json
hw2_spy-1.1.4.dist-info/METADATA
hw2_spy-1.1.4.dist-info/WHEEL
hw2_spy-1.1.4.dist-info/entry_points.txt
hw2_spy-1.1.4.dist-info/RECORD
