Metadata-Version: 2.1
Name: hw2-spy
Version: 1.1.4
Summary: Show curated information about the given Halo Wars 2 players, including a brief overview of their most recent matches' first 12 minutes, by accessing the public API available at https://developer.haloapi.com (a free subscription key is needed).
License: GPL-3.0
Author: Josep M Homs
Author-email: jmhoms@gmail.com
Requires-Python: >=3.10,<4.0
Classifier: License :: OSI Approved :: GNU General Public License v3 (GPLv3)
Classifier: Programming Language :: Python :: 3
Classifier: Programming Language :: Python :: 3.10
Classifier: Programming Language :: Python :: 3.11
Requires-Dist: python-dateutil (>=2.8.2,<3.0.0)
Requires-Dist: textual (>=0.38.0,<0.39.0)
Requires-Dist: types-python-dateutil (>=2.8.19.14,<3.0.0.0)
Requires-Dist: urllib3 (>=2.0.6,<3.0.0)
